{
  "parent": "minecraft:recipes/root",
  "criteria": {
    "has_fluix_crystal": {
      "conditions": {
        "items": [
          {
            "items": [
              "ae2:fluix_crystal"
            ]
          }
        ]
      },
      "trigger": "minecraft:inventory_changed"
    },
    "has_the_recipe": {
      "conditions": {
        "recipe": "neoecoae:structure_terminal"
      },
      "trigger": "minecraft:recipe_unlocked"
    }
  },
  "requirements": [
    [
      "has_fluix_crystal",
      "has_the_recipe"
    ]
  ],
  "rewards": {
    "recipes": [
      "neoecoae:structure_terminal"
    ]
  },
  "sends_telemetry_event": false
}